epfo_scrapper/__init__.py
epfo_scrapper/extractor.py
epfo_scrapper/token_fetcher.py
epfo_scrapper/utils.py
epfo_scrapper-1.2.0.dist-info/METADATA
epfo_scrapper-1.2.0.dist-info/WHEEL
epfo_scrapper-1.2.0.dist-info/top_level.txt
epfo_scrapper-1.2.0.dist-info/RECORD
