Metadata-Version: 2.4
Name: epfo-scrapper
Version: 1.2.0
Summary: Extract employment details from PDF
Author-email: Ramesh Lanke <rameshlanke31@gmail.com>
Requires-Python: >=3.0
Requires-Dist: google-generativeai
Requires-Dist: requests
Requires-Dist: beautifulsoup4
